{
  "data": {
    "type": "dynamic-fixtures",
    "attributes": {
      "synchronize": true,
      "operations": [
        {
          "type": "helper",
          "name": "haveCompany",
          "key": "company",
          "arguments": [{ "status": "approved", "is_active": true }]
        },
        {
          "type": "helper",
          "name": "haveCompanyBusinessUnit",
          "key": "businessUnit",
          "arguments": [{ "fk_company": "#company.id_company" }]
        },
        {
          "type": "helper",
          "name": "havePermissionByKey",
          "key": "placeOrderPermission",
          "arguments": ["PlaceOrderPermissionPlugin"]
        },
        {
          "type": "helper",
          "name": "haveCompanyRoleWithPermissions",
          "key": "buyerRole",
          "arguments": [{ "fk_company": "#company.id_company" }, ["#placeOrderPermission"]]
        },
        {
          "type": "helper",
          "name": "haveFullProduct",
          "key": "product",
          "arguments": [{}, { "idTaxSet": 1 }]
        },
        {
          "type": "helper",
          "name": "havePriceProduct",
          "arguments": [
            {
              "skuProductAbstract": "#product.abstract_sku",
              "skuProduct": "#product.sku",
              "moneyValue": { "netAmount": 30000, "grossAmount": 30000 }
            }
          ]
        },
        {
          "type": "transfer",
          "name": "StoreTransfer",
          "key": "store",
          "arguments": { "id_store": 1 }
        },
        {
          "type": "helper",
          "name": "haveProductInStockForStore",
          "arguments": ["#store", { "sku": "#product.sku", "isNeverOutOfStock": "1" }]
        },
        {
          "type": "helper",
          "name": "haveConfirmedCustomer",
          "key": "buyer",
          "arguments": [{ "registered": "2025-01-01", "password": "change123", "locale_name": "en_US" }]
        },
        {
          "type": "builder",
          "name": "CompanyRoleCollectionBuilder",
          "key": "buyerRoleCollection",
          "arguments": { "roles": ["#buyerRole"] }
        },
        {
          "type": "helper",
          "name": "haveCompanyUser",
          "key": "buyerCompanyUser",
          "arguments": [
            {
              "customer": "#buyer",
              "fk_company": "#company.id_company",
              "company_role_collection": ["#buyerRoleCollection"],
              "fk_company_business_unit": "#businessUnit.id_company_business_unit"
            }
          ]
        },
        {
          "type": "helper",
          "name": "assignCompanyRoles",
          "arguments": ["#buyerCompanyUser", ["#buyerRole"]]
        },
        {
          "type": "helper",
          "name": "havePersistentQuote",
          "key": "quote",
          "arguments": [
            {
              "customer": "#buyer",
              "items": [
                { "sku": "#product.sku", "abstractSku": "#product.abstract_sku", "quantity": 1, "unitPrice": 30000 }
              ]
            }
          ]
        }
      ]
    }
  }
}
